pybitcore/__init__.py
pybitcore/api.py
pybitcore-0.1.dist-info/LICENSE
pybitcore-0.1.dist-info/METADATA
pybitcore-0.1.dist-info/WHEEL
pybitcore-0.1.dist-info/top_level.txt
pybitcore-0.1.dist-info/RECORD
