Metadata-Version: 2.1
Name: pybitcore
Version: 0.1
Summary: Python3 wrapper for the Bitcore API
Home-page: https://github.com/tianshanghong/pybitcore
Author: Wei Wang
Author-email: tianshanghong@outlook.com
License: UNKNOWN
Platform: UNKNOWN
Classifier: Programming Language :: Python :: 3
Classifier: License :: OSI Approved :: MIT License
Classifier: Operating System :: OS Independent
